assess_pps/__init__.py
assess_pps/metrics.py
assess_pps-0.1.1.dist-info/METADATA
assess_pps-0.1.1.dist-info/WHEEL
assess_pps-0.1.1.dist-info/top_level.txt
assess_pps-0.1.1.dist-info/RECORD
