Metadata-Version: 2.1
Name: assess-pps
Version: 0.1.1
Summary: Library for calculating time-depending metrics for pps
Home-page: UNKNOWN
Author: Olha Alieinik
License: UNKNOWN
Platform: UNKNOWN
Requires-Dist: pandas
